pyrsistent_extras/__init__.py
pyrsistent_extras/_pheap.py
pyrsistent_extras/_psequence/__init__.py
pyrsistent_extras/_psequence/_base.py
pyrsistent_extras/_psequence/_c_ext.c
pyrsistent_extras/_psequence/_c_ext.cp312-win32.pyd
pyrsistent_extras/_psequence/_c_ext.h
pyrsistent_extras/_utility.py
pyrsistent_extras/_version.py
pyrsistent_extras/lenses.py
pyrsistent_extras/py.typed
pyrsistent_extras-0.1.1.dist-info/METADATA
pyrsistent_extras-0.1.1.dist-info/WHEEL
pyrsistent_extras-0.1.1.dist-info/entry_points.txt
pyrsistent_extras-0.1.1.dist-info/licenses/LICENSE.mit
pyrsistent_extras-0.1.1.dist-info/RECORD
