Metadata-Version: 2.1
Name: pyrsistent-extras
Version: 0.1.1
Summary: Extra data structures for pyrsistent
Author-Email: mingmingrr <mingmingrr@gmail.com>
License: Copyright (c) 2022 mingmingrr
Classifier: Intended Audience :: Developers
Classifier: License :: OSI Approved :: MIT License
Classifier: Operating System :: OS Independent
Classifier: Programming Language :: Python :: 3.8
Classifier: Programming Language :: Python :: 3.9
Classifier: Programming Language :: Python :: 3.10
Classifier: Programming Language :: Python :: 3.11
Classifier: Programming Language :: Python :: 3.12
Classifier: Programming Language :: Python :: 3.13
Classifier: Programming Language :: Python :: Implementation :: PyPy
Project-URL: Homepage, https://github.com/mingmingrr/pyrsistent-extras
Project-URL: Changelog, https://github.com/mingmingrr/pyrsistent-extras/blob/master/CHANGELOG.md
Project-URL: Docs, https://pyrsistent-extras.readthedocs.io/en/latest
Project-URL: Issues, https://github.com/mingmingrr/pyrsistent-extras/issues
Requires-Python: >=3.8
Requires-Dist: typing-extensions
Requires-Dist: pyrsistent; extra == "test"
Requires-Dist: lenses; extra == "test"
Requires-Dist: pytest; extra == "test"
Requires-Dist: hypothesis; extra == "test"
Requires-Dist: sphinx; extra == "docs"
Requires-Dist: sphinx_rtd_theme; extra == "docs"
Requires-Dist: coverage; extra == "coverage"
Requires-Dist: coveralls; extra == "coverage"
Requires-Dist: cpp-coveralls; extra == "coverage"
Provides-Extra: test
Provides-Extra: docs
Provides-Extra: coverage
